MANIFEST.in
README.rst
setup.py
aliyun_python_sdk_yundun.egg-info/PKG-INFO
aliyun_python_sdk_yundun.egg-info/SOURCES.txt
aliyun_python_sdk_yundun.egg-info/dependency_links.txt
aliyun_python_sdk_yundun.egg-info/requires.txt
aliyun_python_sdk_yundun.egg-info/top_level.txt
aliyunsdkyundun/__init__.py
aliyunsdkyundun/request/__init__.py
aliyunsdkyundun/request/v20150227/AllMalwareNumRequest.py
aliyunsdkyundun/request/v20150227/CurrentDdosAttackNumRequest.py
aliyunsdkyundun/request/v20150227/TodayAegisOnlineRateRequest.py
aliyunsdkyundun/request/v20150227/TodayAllkbpsRequest.py
aliyunsdkyundun/request/v20150227/TodayAllppsRequest.py
aliyunsdkyundun/request/v20150227/TodayBackdoorRequest.py
aliyunsdkyundun/request/v20150227/TodayCrackInterceptRequest.py
aliyunsdkyundun/request/v20150227/TodayMalwareNumRequest.py
aliyunsdkyundun/request/v20150227/TodayqpsByRegionRequest.py
aliyunsdkyundun/request/v20150227/WebAttackNumRequest.py
aliyunsdkyundun/request/v20150227/__init__.py